CHANGES.rst
COPYRIGHT
LICENSE
MANIFEST.in
README.rst
setup.py
tox.ini
aiopyramid/__init__.py
aiopyramid/auth.py
aiopyramid/config.py
aiopyramid/exceptions.py
aiopyramid/helpers.py
aiopyramid/traversal.py
aiopyramid/tweens.py
aiopyramid.egg-info/PKG-INFO
aiopyramid.egg-info/SOURCES.txt
aiopyramid.egg-info/dependency_links.txt
aiopyramid.egg-info/entry_points.txt
aiopyramid.egg-info/not-zip-safe
aiopyramid.egg-info/requires.txt
aiopyramid.egg-info/top_level.txt
aiopyramid/gunicorn/__init__.py
aiopyramid/gunicorn/worker.py
aiopyramid/gunicorn/__pycache__/__init__.cpython-34.pyc
aiopyramid/gunicorn/__pycache__/__init__.cpython-35.pyc
aiopyramid/gunicorn/__pycache__/__init__.cpython-36.pyc
aiopyramid/gunicorn/__pycache__/worker.cpython-34.pyc
aiopyramid/gunicorn/__pycache__/worker.cpython-35.pyc
aiopyramid/gunicorn/__pycache__/worker.cpython-36.pyc
aiopyramid/scaffolds/__init__.py
aiopyramid/scaffolds/__pycache__/__init__.cpython-34.pyc
aiopyramid/scaffolds/__pycache__/__init__.cpython-35.pyc
aiopyramid/scaffolds/__pycache__/__init__.cpython-36.pyc
aiopyramid/scaffolds/aio_starter/CHANGES.rst_tmpl
aiopyramid/scaffolds/aio_starter/MANIFEST.in_tmpl
aiopyramid/scaffolds/aio_starter/README.rst_tmpl
aiopyramid/scaffolds/aio_starter/development.ini_tmpl
aiopyramid/scaffolds/aio_starter/setup.py_tmpl
aiopyramid/scaffolds/aio_starter/+package+/__init__.py_tmpl
aiopyramid/scaffolds/aio_starter/+package+/tests.py_tmpl
aiopyramid/scaffolds/aio_starter/+package+/views.py_tmpl
aiopyramid/scaffolds/aio_websocket/CHANGES.rst_tmpl
aiopyramid/scaffolds/aio_websocket/MANIFEST.in_tmpl
aiopyramid/scaffolds/aio_websocket/README.rst_tmpl
aiopyramid/scaffolds/aio_websocket/development.ini_tmpl
aiopyramid/scaffolds/aio_websocket/setup.py_tmpl
aiopyramid/scaffolds/aio_websocket/+package+/__init__.py_tmpl
aiopyramid/scaffolds/aio_websocket/+package+/tests.py_tmpl
aiopyramid/scaffolds/aio_websocket/+package+/views.py_tmpl
aiopyramid/scaffolds/aio_websocket/+package+/templates/home.jinja2
aiopyramid/websocket/__init__.py
aiopyramid/websocket/exceptions.py
aiopyramid/websocket/helpers.py
aiopyramid/websocket/view.py
aiopyramid/websocket/__pycache__/__init__.cpython-34.pyc
aiopyramid/websocket/__pycache__/__init__.cpython-35.pyc
