Metadata-Version: 1.1
Name: aiopyramid
Version: 0.4.1
Summary: Tools for running pyramid using asyncio.
Home-page: https://github.com/housleyjk/aiopyramid
Author: Jason Housley
Author-email: housleyjk@gmail.com
License: BSD-derived (http://www.repoze.org/LICENSE.txt)
Keywords: pyramid asyncio greenlet wsgi
Platform: UNKNOWN
Classifier: Programming Language :: Python
Classifier: Programming Language :: Python :: 3.3
Classifier: Programming Language :: Python :: 3.4
Classifier: Programming Language :: Python :: 3.5
Classifier: Framework :: Pyramid
Classifier: Topic :: Internet :: WWW/HTTP
Classifier: Topic :: Internet :: WWW/HTTP :: WSGI :: Application
Classifier: Intended Audience :: Developers
Classifier: License :: Repoze Public License
